report_env/__init__.py
report_env/__main__.py
report_env/main.py
smolai-0.1.dist-info/LICENSE
smolai-0.1.dist-info/METADATA
smolai-0.1.dist-info/WHEEL
smolai-0.1.dist-info/entry_points.txt
smolai-0.1.dist-info/RECORD
