Metadata-Version: 2.1
Name: smolai
Version: 0.1
Summary: python version of npx envinfo
License: MIT
Author: swyx
Author-email: swyx@dontemail.me
Requires-Python: >=3.9,<4.0
Classifier: License :: OSI Approved :: MIT License
Classifier: Programming Language :: Python :: 3
Classifier: Programming Language :: Python :: 3.9
Classifier: Programming Language :: Python :: 3.10
Classifier: Programming Language :: Python :: 3.11
